Metadata-Version: 1.0
Name: project-bm
Version: 4.2.0
Summary: Projekt z zajec
Home-page: UNKNOWN
Author: Bartosz Munzel
Author-email: df.bartoszmunzel@gmail.com
License: UNKNOWN
Platform: UNKNOWN
